hier_config/__init__.py
hier_config/base.py
hier_config/child.py
hier_config/children.py
hier_config/constructors.py
hier_config/exceptions.py
hier_config/models.py
hier_config/platforms/__init__.py
hier_config/platforms/arista_eos/__init__.py
hier_config/platforms/arista_eos/driver.py
hier_config/platforms/arista_eos/view.py
hier_config/platforms/cisco_ios/__init__.py
hier_config/platforms/cisco_ios/driver.py
hier_config/platforms/cisco_ios/view.py
hier_config/platforms/cisco_nxos/__init__.py
hier_config/platforms/cisco_nxos/driver.py
hier_config/platforms/cisco_nxos/view.py
hier_config/platforms/cisco_xr/__init__.py
hier_config/platforms/cisco_xr/driver.py
hier_config/platforms/cisco_xr/view.py
hier_config/platforms/driver_base.py
hier_config/platforms/fortinet_fortios/__init__.py
hier_config/platforms/fortinet_fortios/driver.py
hier_config/platforms/functions.py
hier_config/platforms/generic/__init__.py
hier_config/platforms/generic/driver.py
hier_config/platforms/hp_comware5/__init__.py
hier_config/platforms/hp_comware5/driver.py
hier_config/platforms/hp_procurve/__init__.py
hier_config/platforms/hp_procurve/driver.py
hier_config/platforms/hp_procurve/functions.py
hier_config/platforms/hp_procurve/view.py
hier_config/platforms/juniper_junos/__init__.py
hier_config/platforms/juniper_junos/driver.py
hier_config/platforms/models.py
hier_config/platforms/view_base.py
hier_config/platforms/vyos/__init__.py
hier_config/platforms/vyos/driver.py
hier_config/py.typed
hier_config/root.py
hier_config/utils.py
hier_config/workflows.py
hier_config-3.3.0.dist-info/LICENSE
hier_config-3.3.0.dist-info/METADATA
hier_config-3.3.0.dist-info/WHEEL
hier_config-3.3.0.dist-info/RECORD
